hf_argparser/__init__.py
hf_argparser/hf_argparser.py
hf_argparser-0.1.1.dist-info/METADATA
hf_argparser-0.1.1.dist-info/WHEEL
hf_argparser-0.1.1.dist-info/licenses/LICENSE
hf_argparser-0.1.1.dist-info/RECORD
