Metadata-Version: 2.1
Name: hf-argparser
Version: 0.1.1
Summary: Standalone version of the HuggingFace ArgParser from the Transformers library
Author-email: John Henning <john@henning.ai>
License-Expression: Apache-2.0
License-File: LICENSE
Requires-Python: >=3.9
Requires-Dist: pyyaml>=6.0.1
